base/ReportUtil.py
base/__init__.py
base/baseformidasapi.py
base/calculator_asd.py
base/dgncodeutil.py
base/engineers.py
base/engineers_server.py
base/engineers_web.py
base/geometry.py
base/hello.html
base/meshutil.py
base/midasapi.py
base/midasapi.pyi
base/midasutil.py
base/midasutil_server.py
base/midasutil_web.py
base/section_property.py
base/symbol.py
base/test.py
base/testmesh.py
base/unit_converter.py
base/vector.py
base/steel/KS18.json
base/steel/__init__.py
base/steel/steelutil.py
project/__init__.py
project/baseplate_KDS41_30_2022/Test.py
project/baseplate_KDS41_30_2022/__init__.py
project/baseplate_KDS41_30_2022/baseplate_KDS41_30_2022_calc.py
project/baseplate_KDS41_30_2022/baseplate_KDS41_30_2022_report.py
project/sectionproperty/report_sectionproperty.py
tests/__init__.py
tests/test_baseplate_kds.py
mapieng-0.2.5.dist-info/METADATA
mapieng-0.2.5.dist-info/WHEEL
mapieng-0.2.5.dist-info/top_level.txt
mapieng-0.2.5.dist-info/RECORD
