Metadata-Version: 2.1
Name: mapieng
Version: 0.2.5
Summary: mapi engineers
Home-page: https://github.com/MIDASIT-Co-Ltd/engineers-api-python
Author: bschoi
License: MIT
Requires-Dist: mdutils
Requires-Dist: numpy
Requires-Dist: matplotlib
Provides-Extra: server
Requires-Dist: concreteproperties ; extra == 'server'
Requires-Dist: sectionproperties ; extra == 'server'
